djh_mcp/__init__.py
djh_mcp-0.1.0.dist-info/METADATA
djh_mcp-0.1.0.dist-info/WHEEL
djh_mcp-0.1.0.dist-info/entry_points.txt
djh_mcp-0.1.0.dist-info/RECORD
